result/design.sv
`timescale 1ns/1ps

//=============================================================================
// TOP-LEVEL SIMD AI ACCELERATOR MODULE
//=============================================================================
module simd_ai_accelerator #(
    parameter SIMD_LANES = 4,           // Number of parallel MAC units
    parameter DATA_WIDTH = 8,           // Input data width
    parameter WEIGHT_WIDTH = 8,         // Weight width
    parameter ACC_WIDTH = 16            // Accumulator width
)(
    // Clock and Reset
    input  wire clk,
    input  wire rst_n,

    // Control Signals
    input  wire enable,
    input  wire simd_start,

    // SIMD Vector Inputs
    input  wire [SIMD_LANES*DATA_WIDTH-1:0] vec_data_in,
    input  wire [SIMD_LANES*WEIGHT_WIDTH-1:0] vec_weight_in,
    input  wire data_valid,

    // SIMD Vector Outputs
    output reg  [SIMD_LANES*ACC_WIDTH-1:0] vec_mac_out,
    output reg  [SIMD_LANES*8-1:0] vec_activation_out,
    output reg  result_valid,

    // Status Outputs
    output wire busy,
    output wire [7:0] power_status
);

    // Internal wires
    wire gated_clk;
    wire power_gated;
    wire [SIMD_LANES-1:0] mac_done;
    wire [SIMD_LANES-1:0] lane_enable;
    wire all_lanes_done;
    wire [ACC_WIDTH-1:0] mac_results [0:SIMD_LANES-1];
    wire [7:0] activation_results [0:SIMD_LANES-1];

    // FSM states
    localparam IDLE=3'b000, LOAD_VECTORS=3'b001, SIMD_COMPUTE=3'b010,
               ACTIVATION=3'b011, OUTPUT=3'b100;

    reg [2:0] state, next_state;

    assign busy = (state != IDLE);
    assign all_lanes_done = &mac_done;

    // Clock Gating
    clock_gating_cell u_main_clock_gate (
        .clk_in(clk),
        .enable(enable & ~power_gated),
        .test_en(1'b0),
        .gated_clk(gated_clk)
    );

    // Power Gating
    power_gating_controller u_power_gate (
        .clk(gated_clk),
        .rst_n(rst_n),
        .module_active(enable),
        .power_gate_signal(power_gated)
    );

    // SIMD Enable
    assign lane_enable = (state == SIMD_COMPUTE) ? {SIMD_LANES{1'b1}} : {SIMD_LANES{1'b0}};

    // Generate SIMD Lanes
    genvar i;
    generate
        for (i=0; i<SIMD_LANES; i=i+1) begin: LANE
            wire [DATA_WIDTH-1:0] lane_data = vec_data_in[(i+1)*DATA_WIDTH-1 : i*DATA_WIDTH];
            wire [WEIGHT_WIDTH-1:0] lane_weight = vec_weight_in[(i+1)*WEIGHT_WIDTH-1 : i*WEIGHT_WIDTH];

            simd_mac_unit #(.DATA_WIDTH(DATA_WIDTH),.WEIGHT_WIDTH(WEIGHT_WIDTH),.ACC_WIDTH(ACC_WIDTH)) mac_lane (
                .clk(gated_clk),
                .rst_n(rst_n),
                .enable(lane_enable[i]),
                .data_in(lane_data),
                .weight_in(lane_weight),
                .mac_result(mac_results[i]),
                .mac_done(mac_done[i])
            );

            activation_function act_lane (
                .clk(gated_clk),
                .rst_n(rst_n),
                .data_in(mac_results[i]),
                .activation_out(activation_results[i])
            );
        end
    endgenerate

    // FSM
    always @(posedge gated_clk or negedge rst_n)
        if(!rst_n) state <= IDLE; else state <= next_state;

    always @(*) begin
        next_state = state;
        case(state)
            IDLE:        if(enable && simd_start && data_valid) next_state = LOAD_VECTORS;
            LOAD_VECTORS: next_state = SIMD_COMPUTE;
            SIMD_COMPUTE: if(all_lanes_done) next_state = ACTIVATION;
            ACTIVATION:   next_state = OUTPUT;
            OUTPUT:       next_state = IDLE;
            default:      next_state = IDLE;
        endcase
    end

    // Output logic (fixed: no variable part-select)
    always @(posedge gated_clk or negedge rst_n) begin
        if(!rst_n) begin
            vec_mac_out <= 0;
            vec_activation_out <= 0;
            result_valid <= 0;
        end else if(state == OUTPUT) begin
            vec_mac_out <= {mac_results[3], mac_results[2], mac_results[1], mac_results[0]};
            vec_activation_out <= {activation_results[3], activation_results[2], activation_results[1], activation_results[0]};
            result_valid <= 1;
        end else begin
            result_valid <= 0;
        end
    end

    assign power_status = {state[2:0], all_lanes_done, power_gated, result_valid, busy, 1'b0};

endmodule


//-----------------------------------------------------------------------------
// MAC UNIT
//-----------------------------------------------------------------------------
module simd_mac_unit #(parameter DATA_WIDTH=8,WEIGHT_WIDTH=8,ACC_WIDTH=16)(
    input wire clk, rst_n, enable,
    input wire [DATA_WIDTH-1:0] data_in,
    input wire [WEIGHT_WIDTH-1:0] weight_in,
    output reg [ACC_WIDTH-1:0] mac_result,
    output reg mac_done
);
    reg [ACC_WIDTH-1:0] acc;
    reg [1:0] s;
    localparam IDLE=0, MULT=1, ACCUM=2, DONE=3;
    always @(posedge clk or negedge rst_n) begin
        if(!rst_n) begin s<=IDLE; acc<=0; mac_result<=0; mac_done<=0; end
        else case(s)
            IDLE: begin mac_done<=0; if(enable) s<=MULT; end
            MULT: begin acc<=data_in*weight_in; s<=ACCUM; end
            ACCUM: begin mac_result<=acc; mac_done<=1; s<=DONE; end
            DONE: s<=IDLE;
        endcase
    end
endmodule


//-----------------------------------------------------------------------------
// CLOCK GATE
//-----------------------------------------------------------------------------
module clock_gating_cell(input wire clk_in, enable, test_en, output wire gated_clk);
    reg en_latched;
    always @(*) if(!clk_in) en_latched = enable | test_en;
    assign gated_clk = clk_in & en_latched;
endmodule


//-----------------------------------------------------------------------------
// POWER GATE
//-----------------------------------------------------------------------------
module power_gating_controller(input wire clk, rst_n, module_active, output reg power_gate_signal);
    reg [3:0] idle_count;
    localparam IDLE_THRESHOLD = 10;
    always @(posedge clk or negedge rst_n)
        if(!rst_n) begin idle_count<=0; power_gate_signal<=0; end
        else if(module_active) begin idle_count<=0; power_gate_signal<=0; end
        else if(idle_count < IDLE_THRESHOLD) idle_count<=idle_count+1;
        else power_gate_signal<=1;
endmodule


//-----------------------------------------------------------------------------
// ACTIVATION FUNCTION (ReLU-like)
//-----------------------------------------------------------------------------
module activation_function(input wire clk, rst_n, input wire [15:0] data_in, output reg [7:0] activation_out);
    always @(posedge clk or negedge rst_n)
        if(!rst_n) activation_out <= 0;
        else if(data_in[15]) activation_out <= 0;
        else activation_out <= (|data_in[15:8]) ? 8'hFF : data_in[7:0];
endmodule

result/testbench.sv
`timescale 1ns/1ps
module tb_simd_ai_accelerator;

    parameter SIMD_LANES=4, DATA_WIDTH=8, WEIGHT_WIDTH=8, ACC_WIDTH=16;
    reg clk, rst_n, enable, simd_start, data_valid;
    reg [SIMD_LANES*DATA_WIDTH-1:0] vec_data_in;
    reg [SIMD_LANES*WEIGHT_WIDTH-1:0] vec_weight_in;
    wire [SIMD_LANES*ACC_WIDTH-1:0] vec_mac_out;
    wire [SIMD_LANES*8-1:0] vec_activation_out;
    wire result_valid, busy;
    wire [7:0] power_status;

    always #50 clk = ~clk;

    simd_ai_accelerator dut (
        .clk(clk), .rst_n(rst_n),
        .enable(enable), .simd_start(simd_start),
        .vec_data_in(vec_data_in), .vec_weight_in(vec_weight_in),
        .data_valid(data_valid),
        .vec_mac_out(vec_mac_out),
        .vec_activation_out(vec_activation_out),
        .result_valid(result_valid),
        .busy(busy), .power_status(power_status)
    );

    initial begin
        $dumpfile("SMID_Chip.vcd");
        $dumpvars(0, tb_simd_ai_accelerator);

        clk=0; rst_n=0; enable=0; simd_start=0; data_valid=0;
        vec_data_in=0; vec_weight_in=0;

        #200 rst_n=1; #100;
        $display("===== SIMD AI Accelerator Simulation =====");

        // Test 1
        enable=1; simd_start=1; data_valid=1;
        vec_data_in = {8'd25,8'd15,8'd20,8'd10};
        vec_weight_in = {8'd2,8'd7,8'd3,8'd5};
        #200 simd_start=0;
        wait(result_valid);
        $display("[Test1] MAC Results: %d %d %d %d",
                 vec_mac_out[15:0], vec_mac_out[31:16], vec_mac_out[47:32], vec_mac_out[63:48]);

        #500;
        $display("Simulation complete!");
        $finish;
    end
endmodule

result/SMID_Chip.vcd
$date
	Mon Oct 27 12:24:18 2025
$end
$version
	Icarus Verilog
$end
$timescale
	1ps
$end
$scope module tb_simd_ai_accelerator $end
$var wire 64 ! vec_mac_out [63:0] $end
$var wire 32 " vec_activation_out [31:0] $end
$var wire 1 # result_valid $end
$var wire 8 $ power_status [7:0] $end
$var wire 1 % busy $end
$var parameter 32 & ACC_WIDTH $end
$var parameter 32 ' DATA_WIDTH $end
$var parameter 32 ( SIMD_LANES $end
$var parameter 32 ) WEIGHT_WIDTH $end
$var reg 1 * clk $end
$var reg 1 + data_valid $end
$var reg 1 , enable $end
$var reg 1 - rst_n $end
$var reg 1 . simd_start $end
$var reg 32 / vec_data_in [31:0] $end
$var reg 32 0 vec_weight_in [31:0] $end
$scope module dut $end
$var wire 1 * clk $end
$var wire 1 + data_valid $end
$var wire 1 , enable $end
$var wire 1 - rst_n $end
$var wire 1 . simd_start $end
$var wire 32 1 vec_data_in [31:0] $end
$var wire 32 2 vec_weight_in [31:0] $end
$var wire 8 3 power_status [7:0] $end
$var wire 1 4 power_gated $end
$var wire 4 5 mac_done [3:0] $end
$var wire 4 6 lane_enable [3:0] $end
$var wire 1 7 gated_clk $end
$var wire 1 % busy $end
$var wire 1 8 all_lanes_done $end
$var parameter 32 9 ACC_WIDTH $end
$var parameter 3 : ACTIVATION $end
$var parameter 32 ; DATA_WIDTH $end
$var parameter 3 < IDLE $end
$var parameter 3 = LOAD_VECTORS $end
$var parameter 3 > OUTPUT $end
$var parameter 3 ? SIMD_COMPUTE $end
$var parameter 32 @ SIMD_LANES $end
$var parameter 32 A WEIGHT_WIDTH $end
$var reg 3 B next_state [2:0] $end
$var reg 1 # result_valid $end
$var reg 3 C state [2:0] $end
$var reg 32 D vec_activation_out [31:0] $end
$var reg 64 E vec_mac_out [63:0] $end
$scope begin LANE[0] $end
$var wire 8 F lane_data [7:0] $end
$var wire 8 G lane_weight [7:0] $end
$var parameter 2 H i $end
$scope module act_lane $end
$var wire 1 - rst_n $end
$var wire 16 I data_in [15:0] $end
$var wire 1 7 clk $end
$var reg 8 J activation_out [7:0] $end
$upscope $end
$scope module mac_lane $end
$var wire 8 K data_in [7:0] $end
$var wire 1 L enable $end
$var wire 1 - rst_n $end
$var wire 8 M weight_in [7:0] $end
$var wire 1 7 clk $end
$var parameter 32 N ACCUM $end
$var parameter 32 O ACC_WIDTH $end
$var parameter 32 P DATA_WIDTH $end
$var parameter 32 Q DONE $end
$var parameter 32 R IDLE $end
$var parameter 32 S MULT $end
$var parameter 32 T WEIGHT_WIDTH $end
$var reg 16 U acc [15:0] $end
$var reg 1 V mac_done $end
$var reg 16 W mac_result [15:0] $end
$var reg 2 X s [1:0] $end
$upscope $end
$upscope $end
$scope begin LANE[1] $end
$var wire 8 Y lane_data [7:0] $end
$var wire 8 Z lane_weight [7:0] $end
$var parameter 2 [ i $end
$scope module act_lane $end
$var wire 1 - rst_n $end
$var wire 16 \ data_in [15:0] $end
$var wire 1 7 clk $end
$var reg 8 ] activation_out [7:0] $end
$upscope $end
$scope module mac_lane $end
$var wire 8 ^ data_in [7:0] $end
$var wire 1 _ enable $end
$var wire 1 - rst_n $end
$var wire 8 ` weight_in [7:0] $end
$var wire 1 7 clk $end
$var parameter 32 a ACCUM $end
$var parameter 32 b ACC_WIDTH $end
$var parameter 32 c DATA_WIDTH $end
$var parameter 32 d DONE $end
$var parameter 32 e IDLE $end
$var parameter 32 f MULT $end
$var parameter 32 g WEIGHT_WIDTH $end
$var reg 16 h acc [15:0] $end
$var reg 1 i mac_done $end
$var reg 16 j mac_result [15:0] $end
$var reg 2 k s [1:0] $end
$upscope $end
$upscope $end
$scope begin LANE[2] $end
$var wire 8 l lane_data [7:0] $end
$var wire 8 m lane_weight [7:0] $end
$var parameter 3 n i $end
$scope module act_lane $end
$var wire 1 - rst_n $end
$var wire 16 o data_in [15:0] $end
$var wire 1 7 clk $end
$var reg 8 p activation_out [7:0] $end
$upscope $end
$scope module mac_lane $end
$var wire 8 q data_in [7:0] $end
$var wire 1 r enable $end
$var wire 1 - rst_n $end
$var wire 8 s weight_in [7:0] $end
$var wire 1 7 clk $end
$var parameter 32 t ACCUM $end
$var parameter 32 u ACC_WIDTH $end
$var parameter 32 v DATA_WIDTH $end
$var parameter 32 w DONE $end
$var parameter 32 x IDLE $end
$var parameter 32 y MULT $end
$var parameter 32 z WEIGHT_WIDTH $end
$var reg 16 { acc [15:0] $end
$var reg 1 | mac_done $end
$var reg 16 } mac_result [15:0] $end
$var reg 2 ~ s [1:0] $end
$upscope $end
$upscope $end
$scope begin LANE[3] $end
$var wire 8 !" lane_data [7:0] $end
$var wire 8 "" lane_weight [7:0] $end
$var parameter 3 #" i $end
$scope module act_lane $end
$var wire 1 - rst_n $end
$var wire 16 $" data_in [15:0] $end
$var wire 1 7 clk $end
$var reg 8 %" activation_out [7:0] $end
$upscope $end
$scope module mac_lane $end
$var wire 8 &" data_in [7:0] $end
$var wire 1 '" enable $end
$var wire 1 - rst_n $end
$var wire 8 (" weight_in [7:0] $end
$var wire 1 7 clk $end
$var parameter 32 )" ACCUM $end
$var parameter 32 *" ACC_WIDTH $end
$var parameter 32 +" DATA_WIDTH $end
$var parameter 32 ," DONE $end
$var parameter 32 -" IDLE $end
$var parameter 32 ." MULT $end
$var parameter 32 /" WEIGHT_WIDTH $end
$var reg 16 0" acc [15:0] $end
$var reg 1 1" mac_done $end
$var reg 16 2" mac_result [15:0] $end
$var reg 2 3" s [1:0] $end
$upscope $end
$upscope $end
$scope module u_main_clock_gate $end
$var wire 1 * clk_in $end
$var wire 1 4" enable $end
$var wire 1 7 gated_clk $end
$var wire 1 5" test_en $end
$var reg 1 6" en_latched $end
$upscope $end
$scope module u_power_gate $end
$var wire 1 7 clk $end
$var wire 1 , module_active $end
$var wire 1 - rst_n $end
$var parameter 32 7" IDLE_THRESHOLD $end
$var reg 4 8" idle_count [3:0] $end
$var reg 1 4 power_gate_signal $end
$upscope $end
$upscope $end
$upscope $end
$enddefinitions $end
$comment Show the parameter values. $end
$dumpall
b1010 7"
b1000 /"
b1 ."
b0 -"
b11 ,"
b1000 +"
b10000 *"
b10 )"
b11 #"
b1000 z
b1 y
b0 x
b11 w
b1000 v
b10000 u
b10 t
b10 n
b1000 g
b1 f
b0 e
b11 d
b1000 c
b10000 b
b10 a
b1 [
b1000 T
b1 S
b0 R
b11 Q
b1000 P
b10000 O
b10 N
b0 H
b1000 A
b100 @
b10 ?
b100 >
b1 =
b0 <
b1000 ;
b11 :
b10000 9
b1000 )
b100 (
b1000 '
b10000 &
$end
#0
$dumpvars
b0 8"
06"
05"
04"
b0 3"
b0 2"
01"
b0 0"
b0 ("
0'"
b0 &"
b0 %"
b0 $"
b0 ""
b0 !"
b0 ~
b0 }
0|
b0 {
b0 s
0r
b0 q
b0 p
b0 o
b0 m
b0 l
b0 k
b0 j
0i
b0 h
b0 `
0_
b0 ^
b0 ]
b0 \
b0 Z
b0 Y
b0 X
b0 W
0V
b0 U
b0 M
0L
b0 K
b0 J
b0 I
b0 G
b0 F
b0 E
b0 D
b0 C
b0 B
08
07
b0 6
b0 5
04
b0 3
b0 2
b0 1
b0 0
b0 /
0.
0-
0,
0+
0*
0%
b0 $
0#
b0 "
b0 !
$end
#50000
1*
#100000
0*
#150000
1*
#200000
0*
1-
#250000
1*
#300000
16"
b101 G
b101 M
b11 Z
b11 `
b111 m
b111 s
b10 ""
b10 ("
b1010 F
b1010 K
b10100 Y
b10100 ^
b1111 l
b1111 q
b11001 !"
b11001 &"
14"
b1 B
0*
b10000001110000001100000101 0
b10000001110000001100000101 2
b11001000011110001010000001010 /
b11001000011110001010000001010 1
1+
1.
1,
#350000
b10 B
1%
b100010 $
b100010 3
b1 C
17
1*
#400000
07
0*
#450000
1'"
1r
1_
1L
b1111 6
b1000010 $
b1000010 3
b10 C
17
1*
#500000
07
0*
0.
#550000
b1 3"
b1 ~
b1 k
b1 X
17
1*
#600000
07
0*
#650000
b10 X
b110010 U
b10 k
b111100 h
b10 ~
b1101001 {
b10 3"
b110010 0"
17
1*
#700000
07
0*
#750000
b11 B
b11 3"
b1010010 $
b1010010 3
18
11"
b110010 $"
b110010 2"
b11 ~
1|
b1101001 o
b1101001 }
b11 k
1i
b111100 \
b111100 j
b11 X
b1111 5
1V
b110010 I
b110010 W
17
1*
#800000
07
0*
#850000
0'"
0r
0_
0L
b100 B
b0 6
b0 X
b110010 J
b0 k
b111100 ]
b0 ~
b1101001 p
b0 3"
b110010 %"
b1110010 $
b1110010 3
b11 C
17
1*
#900000
07
0*
#950000
b0 B
b100 C
01"
0|
0i
b10000010 $
b10000010 3
08
b0 5
0V
17
1*
#1000000
07
0*
#1050000
0%
b0 C
b100 $
b100 3
1#
b110010011010010011110000110010 "
b110010011010010011110000110010 D
b110010000000000110100100000000001111000000000000110010 !
b110010000000000110100100000000001111000000000000110010 E
17
1*
#1100000
07
0*
#1150000
b0 $
b0 3
0#
17
1*
